pictone/__init__.py
pictone/__main__.py
pictone/cli.py
pictone/exception.py
pictone/parser.py
pictone/sampler.py
pictone-1.0.0.dist-info/LICENSE
pictone-1.0.0.dist-info/METADATA
pictone-1.0.0.dist-info/WHEEL
pictone-1.0.0.dist-info/entry_points.txt
pictone-1.0.0.dist-info/top_level.txt
pictone-1.0.0.dist-info/RECORD
