Metadata-Version: 2.1
Name: pictone
Version: 1.0.0
Summary: Fun image to Vectorscope audio CLI tool. With support for complex sequences.
Home-page: https://github.com/EterDelta/PicTone
Author: EterDelta
License: MIT
Classifier: Intended Audience :: End Users/Desktop
Classifier: Intended Audience :: Education
Classifier: Topic :: Scientific/Engineering :: Visualization
Classifier: Topic :: Artistic Software
Classifier: License :: OSI Approved :: MIT License
Classifier: Operating System :: OS Independent
Classifier: Programming Language :: Python
Requires-Python: >=3.6
License-File: LICENSE
Requires-Dist: opencv-python
Requires-Dist: numpy
